hope_smart_export/__init__.py
hope_smart_export/admin.py
hope_smart_export/apps.py
hope_smart_export/models.py
hope_smart_export/utils.py
hope_smart_export/exporters/__init__.py
hope_smart_export/exporters/base.py
hope_smart_export/exporters/csv.py
hope_smart_export/exporters/registry.py
hope_smart_export/exporters/txt.py
hope_smart_export/exporters/xls.py
hope_smart_export/migrations/0001_initial.py
hope_smart_export/migrations/__init__.py
hope_smart_export/templates/admin/hope_smart_export/action_form.html
hope_smart_export/templates/admin/hope_smart_export/configure.html
hope_smart_export/templates/admin/hope_smart_export/test.html
hope_smart_export-0.3.0.dist-info/METADATA
hope_smart_export-0.3.0.dist-info/WHEEL
hope_smart_export-0.3.0.dist-info/top_level.txt
hope_smart_export-0.3.0.dist-info/RECORD
