Metadata-Version: 2.1
Name: hope-smart-export
Version: 0.3.0
License: MIT
Project-URL: Homepage, https://github.com/unicef/hope-smart-export
Project-URL: Documentation, https://unicef.github.io/hope-smart-export/
Requires-Python: >=3.11
Requires-Dist: django-admin-extra-buttons >=1.5.8
Requires-Dist: django-adminactions >=2.3.0
Requires-Dist: django-strategy-field >=3.1.0
Requires-Dist: xlsxwriter >=3.2.0
Provides-Extra: docs
Requires-Dist: mkdocs >=1.6.1 ; extra == 'docs'
Requires-Dist: mkdocs-material >=9.5.36 ; extra == 'docs'
Requires-Dist: mkdocs-awesome-pages-plugin >=2.9.3 ; extra == 'docs'
Requires-Dist: mkdocstrings-python ; extra == 'docs'
